ai_gateway/.env-example
ai_gateway/__init__.py
ai_gateway/__main__.py
ai_gateway/alembic/README
ai_gateway/alembic/env.py
ai_gateway/alembic/script.py.mako
ai_gateway/alembic/versions/9c1bf0cf8128_初始化数据表.py
ai_gateway/api/__init__.py
ai_gateway/api/v1/__init__.py
ai_gateway/api/v1/business/__init__.py
ai_gateway/api/v1/business/ashare_dividend.py
ai_gateway/api/v1/business/etf.py
ai_gateway/api/v1/business/opportunity.py
ai_gateway/api/v1/common/approve.py
ai_gateway/api/v1/common/collection.py
ai_gateway/api/v1/common/email.py
ai_gateway/api/v1/common/pptx_operation.py
ai_gateway/api/v1/common/subscription.py
ai_gateway/api/v1/common/user_extend.py
ai_gateway/api/v1/demo/__init__.py
ai_gateway/api/v1/demo/db_curd_user.py
ai_gateway/api/v1/demo/dbs_test.py
ai_gateway/api/v1/demo/exception_example.py
ai_gateway/api/v1/demo/llm.py
ai_gateway/api/v1/demo/simple.py
ai_gateway/api/v1/plat/__init__.py
ai_gateway/api/v1/plat/api_key.py
ai_gateway/api/v1/plat/app.py
ai_gateway/api/v1/plat/auth.py
ai_gateway/api/v1/plat/interface.py
ai_gateway/api/v1/plat/interface_auth.py
ai_gateway/api/v1/plat/interface_log.py
ai_gateway/config.py
ai_gateway/core/__init__.py
ai_gateway/core/init_app.py
ai_gateway/core/log.py
ai_gateway/core/middleware.py
ai_gateway/core/schedule.py
ai_gateway/core/token.py
ai_gateway/curd/__init__.py
ai_gateway/curd/base.py
ai_gateway/curd/demo/__init__.py
ai_gateway/curd/demo/user.py
ai_gateway/curd/plat/api_key.py
ai_gateway/curd/plat/app.py
ai_gateway/curd/plat/interface.py
ai_gateway/curd/plat/interface_auth.py
ai_gateway/curd/plat/interface_log.py
ai_gateway/dbs/__init__.py
ai_gateway/dbs/db.py
ai_gateway/dbs/es_tool.py
ai_gateway/dbs/minio_tool.py
ai_gateway/dbs/redis_tool.py
ai_gateway/dbs/s3_tool.py
ai_gateway/main.py
ai_gateway/main_fastapi_mcp.py
ai_gateway/main_fastmcp_http.py
ai_gateway/main_fastmcp_http_mount.py
ai_gateway/main_fastmcp_stdio.py
ai_gateway/main_fastmcp_stdio_mount.py
ai_gateway/misc/instantclient_21_17/BASIC_LICENSE
ai_application_gateway-0.1.5.dist-info/METADATA
ai_application_gateway-0.1.5.dist-info/WHEEL
ai_application_gateway-0.1.5.dist-info/entry_points.txt
ai_application_gateway-0.1.5.dist-info/RECORD
