Metadata-Version: 2.3
Name: ai-application-gateway
Version: 0.1.5
Summary: API看板服务
Author: GDX
Author-email: guandianxi@sensedai.ai
Requires-Python: >=3.10,<3.12
Classifier: Programming Language :: Python :: 3
Classifier: Programming Language :: Python :: 3.10
Classifier: Programming Language :: Python :: 3.11
Requires-Dist: aioboto3 (>=14.0.0,<15.0.0)
Requires-Dist: aiohttp (>=3.11.11,<4.0.0)
Requires-Dist: aiomysql (>=0.2.0,<0.3.0)
Requires-Dist: alembic (>=1.14.0,<2.0.0)
Requires-Dist: anyio (>=4.8.0,<5.0.0)
Requires-Dist: apscheduler (>=3.11.0,<4.0.0)
Requires-Dist: croniter (>=6.0.0,<7.0.0)
Requires-Dist: dynaconf (>=3.2.6,<4.0.0)
Requires-Dist: elasticsearch (>=8.17.1,<9.0.0)
Requires-Dist: fastapi (>=0.115.6,<0.116.0)
Requires-Dist: fastapi-mcp (>=0.3.4,<0.4.0)
Requires-Dist: fastmcp (>=2.7.1,<3.0.0)
Requires-Dist: greenlet (>=3.1.1,<4.0.0)
Requires-Dist: httpx (>=0.28.1,<0.29.0)
Requires-Dist: lazify (>=0.4.0,<0.5.0)
Requires-Dist: limiter (>=0.5.0,<0.6.0)
Requires-Dist: loguru (>=0.7.3,<0.8.0)
Requires-Dist: minio (>=7.2.15,<8.0.0)
Requires-Dist: oracledb (>=3.1.0,<4.0.0)
Requires-Dist: pandas (>=2.2.3,<3.0.0)
Requires-Dist: prometheus-fastapi-instrumentator (>=7.0.2,<8.0.0)
Requires-Dist: pydantic (>=2.10.6,<3.0.0)
Requires-Dist: pymysql (>=1.1.1,<2.0.0)
Requires-Dist: pypinyin (>=0.54.0,<0.55.0)
Requires-Dist: python-jose (>=3.3.0,<4.0.0)
Requires-Dist: python-multipart (>=0.0.20,<0.0.21)
Requires-Dist: python-pptx (>=1.0.2,<2.0.0)
Requires-Dist: pyyaml (>=6.0.2,<7.0.0)
Requires-Dist: redis (>=5.2.1,<6.0.0)
Requires-Dist: requests (>=2.32.3,<3.0.0)
Requires-Dist: shortuuid (>=1.0.13,<2.0.0)
Requires-Dist: sqlalchemy (>=2.0.37,<3.0.0)
Requires-Dist: sqlmodel (>=0.0.22,<0.0.23)
Requires-Dist: sse-starlette (>=2.2.1,<3.0.0)
Requires-Dist: starlette (>=0.41.3,<0.42.0)
Requires-Dist: uvicorn (>=0.34.0,<0.35.0)
